{
  "creds": {
    "noiseKey": {
      "private": {
        "type": "Buffer",
        "data": "SFPvr+8gy9oFcNA9aujGwAD/s2fCoTD4pRT/WV37LHY="
      },
      "public": {
        "type": "Buffer",
        "data": "PEgObpjYWVWIagttWt5TDYTor+H0pO4Vqt2SlhRdWjw="
      }
    },
    "signedIdentityKey": {
      "private": {
        "type": "Buffer",
        "data": "YC2H9EF1yi0GufmCPeDtH9a45EgCggNmZu480Pi6Wls="
      },
      "public": {
        "type": "Buffer",
        "data": "NdQWBbzmiJREjWsJhS2zayemSKJ3ysOdy8624xSWcWs="
      }
    },
    "signedPreKey": {
      "keyPair": {
        "private": {
          "type": "Buffer",
          "data": "SGHkfLqEzs1vNl5bblfVtSS/sz3lVVsvLibHzcB06WQ="
        },
        "public": {
          "type": "Buffer",
          "data": "tBJZzLCY2j0AdBjIAgKsHY/E6YgPl7KCAhmrADaZmyo="
        }
      },
      "signature": {
        "type": "Buffer",
        "data": "l5BF8PTREkc+08L6vGD7idCWT5wWSOtlrEV+91YnrcS2AC20DD5cGsJDh8ecGV5kE2Kuqk+RvOil9hu3C78ICw=="
      },
      "keyId": 1
    },
    "registrationId": 231,
    "advSecretKey": "SbP7gusSB7479Fc91vTaBeo24HcvcSnE5EmLNo5WPSs=",
    "processedHistoryMessages": [
      {
        "key": {
          "remoteJid": "6281998199848@s.whatsapp.net",
          "fromMe": true,
          "id": "9179811F0D84A47275E722C86E331AE4"
        },
        "messageTimestamp": 1673225449
      },
      {
        "key": {
          "remoteJid": "6281998199848@s.whatsapp.net",
          "fromMe": true,
          "id": "8A9A6091DE45493C3EDC7A40BCAF8A78"
        },
        "messageTimestamp": 1673225450
      },
      {
        "key": {
          "remoteJid": "6281998199848@s.whatsapp.net",
          "fromMe": true,
          "id": "D0D6B83AC32A14451B269B076DB57E53"
        },
        "messageTimestamp": 1673225458
      }
    ],
    "nextPreKeyId": 63,
    "firstUnuploadedPreKeyId": 63,
    "accountSettings": {
      "unarchiveChats": false
    },
    "account": {
      "details": "CLjS3akDEOPJ7Z0GGAE=",
      "accountSignatureKey": "fZaHLK1x0dzQ/D8PMwgOhE+WA8sTKI6wgren/nVDnno=",
      "accountSignature": "U+D7ORXjFrF58i02oz/fIXmI95XHNhWYURDYYAeXUmgfaOvGoyPs8iHVXoZ4WkAOk+Ecwdjocjb8iU08ivVgCw==",
      "deviceSignature": "6hHh3qmDOzAp5pWGGzb0ZGdW2HB4OgoiRaMdUTHibyNjqw110qSHWoedGOe3pawRr95htVhWLlxMKL6BoTH4Aw=="
    },
    "me": {
      "id": "6281998199848:2@s.whatsapp.net",
      "name": "⃟ ssv?"
    },
    "signalIdentities": [
      {
        "identifier": {
          "name": "6281998199848:2@s.whatsapp.net",
          "deviceId": 0
        },
        "identifierKey": {
          "type": "Buffer",
          "data": "BX2WhyytcdHc0Pw/DzMIDoRPlgPLEyiOsIK3p/51Q556"
        }
      }
    ],
    "platform": "android",
    "lastAccountSyncTimestamp": 1673225447,
    "myAppStateKeyId": "AAAAAJ7+"
  },
  "keys": {
    "preKeys": {
      "1": {
        "private": {
          "type": "Buffer",
          "data": "sKrpRTQSLEQIJJjdDMtTzJntfxtvoTyo95pREv8hn0k="
        },
        "public": {
          "type": "Buffer",
          "data": "q/dYDn4MIcuKys8LwhcnSZiptsWIleFstSlaEyZ6Ynk="
        }
      },
      "2": {
        "private": {
          "type": "Buffer",
          "data": "qD0CQvRi1gp/Mj+2/DMgc9keKUscXUNRA4PVaILpSGc="
        },
        "public": {
          "type": "Buffer",
          "data": "IsAri368USYb5TbnSwot4RQDVyPdlIVswFZqwm0ixU0="
        }
      },
      "3": {
        "private": {
          "type": "Buffer",
          "data": "WMV2CMCJjOxMMKjUhJipBNbupbUpugR7DzkvWuf5vlk="
        },
        "public": {
          "type": "Buffer",
          "data": "ec/d8r8kwtq0tsiXxpie1Q+KL5y0uUD1pDoKN+3UKCU="
        }
      },
      "4": {
        "private": {
          "type": "Buffer",
          "data": "8CS58NY/XFWlxNJCZ+mxeONgsEXGy8B31ax2JzkVpHo="
        },
        "public": {
          "type": "Buffer",
          "data": "Q3jvc29RZ+UZTOTKklTUAsidJJfsQ2rduug2QVRjZ1k="
        }
      },
      "5": {
        "private": {
          "type": "Buffer",
          "data": "sBmwrwIfZCIvPVK3DdbRL14m0PGzJd/yhW6XmZqye3I="
        },
        "public": {
          "type": "Buffer",
          "data": "c86WHnisJUNNGVK8sLM+Up1us/JtSk1gwIVpAsbllAg="
        }
      },
      "6": {
        "private": {
          "type": "Buffer",
          "data": "kLTJPiYbeiI/dPwf3MfvE3EvGmip5Rt4RKrj2zCPDEs="
        },
        "public": {
          "type": "Buffer",
          "data": "oxbm+KIZfZ1ojX1a87SvTXOvCdjAvwdjSDWgNMK5ynQ="
        }
      },
      "7": {
        "private": {
          "type": "Buffer",
          "data": "KO+Jo9XI/95IbPY3oB0gAYsYCFFMsd1IHudRYhc7CEI="
        },
        "public": {
          "type": "Buffer",
          "data": "jWUR6uPfPtZJ0HhAywamqMod2lDRUhL9a8eYTLKIuyM="
        }
      },
      "8": {
        "private": {
          "type": "Buffer",
          "data": "CJiuURYIhAGrRJr3bcHSdh41eK8ErX2VpHZ8f9+FMHg="
        },
        "public": {
          "type": "Buffer",
          "data": "m0OfeXogpF/nz36NAJdRUQu3uyRYu9VCh5Fp+LIqm0E="
        }
      },
      "9": {
        "private": {
          "type": "Buffer",
          "data": "yBw+E8Kei+XCU7HuWGnV4ulIWiCOMocNUhLZNgtif2M="
        },
        "public": {
          "type": "Buffer",
          "data": "rnSl021alzDSoRIW5b2l3ejBGAu2+FV3bTXs2dyx/Vg="
        }
      },
      "10": {
        "private": {
          "type": "Buffer",
          "data": "KMTKKaPEhRRlwmY8HpcpRZT+SscG4J4uP1jDtq134Ek="
        },
        "public": {
          "type": "Buffer",
          "data": "wykd8He1gjvoISBZRLSJYOjXonaOF3gQGBNHFXrypCw="
        }
      },
      "11": {
        "private": {
          "type": "Buffer",
          "data": "GHr7hvMP7Qt8sShiz6IxImUIJIcH8IJ/jXUQH0jj4no="
        },
        "public": {
          "type": "Buffer",
          "data": "igdM5AXtMb8YI26jyEzXmHV9YqE1RJyYWw13IPkha1Y="
        }
      },
      "12": {
        "private": {
          "type": "Buffer",
          "data": "WLX5TipRFjbZqxKOIjWD4IOklSTidwQC4cPr3OR1xFM="
        },
        "public": {
          "type": "Buffer",
          "data": "P0isiAM+riuiajElqsVxy1m9aqm5h9n79xFapW+YHF4="
        }
      },
      "13": {
        "private": {
          "type": "Buffer",
          "data": "GPjQ/uilQR4Ho9mRgf1qThww1uu9dGlPrC20aqcJUn8="
        },
        "public": {
          "type": "Buffer",
          "data": "Q1yCgx29T34K5Bgp38DJw1yiQRhWaArE57IkRwIT4xI="
        }
      },
      "14": {
        "private": {
          "type": "Buffer",
          "data": "uNuUhACEFGH+8YBnk4e2CpzVD1VGSrqyd/CaTg/aLWA="
        },
        "public": {
          "type": "Buffer",
          "data": "kzAvTetkeWERwWRG3JLuvVtmVPIP7lutVkgSNxJWtyw="
        }
      },
      "15": {
        "private": {
          "type": "Buffer",
          "data": "UAs75oqTGeksJDWBzBhgAmVzOYut2Ezl6g28JnEpyUc="
        },
        "public": {
          "type": "Buffer",
          "data": "q2BF8zWvNIZ24H4kU4BpaMV5AZLrtzcEzjfPq9n6p0g="
        }
      },
      "16": null,
      "17": null,
      "18": null,
      "19": {
        "private": {
          "type": "Buffer",
          "data": "gHdId71m4TEf9dnCzW5HOaUsyCMqrELEZjloI9jrukk="
        },
        "public": {
          "type": "Buffer",
          "data": "zhjzoNPGJha9o1e/4D58pkH8OVoE9G7YJmMayeDHDw8="
        }
      },
      "20": {
        "private": {
          "type": "Buffer",
          "data": "WMkqG/e4/dcCOJln1jgyFzln6soDi78UQoNbrW59NmE="
        },
        "public": {
          "type": "Buffer",
          "data": "NqjpX3SsmO1L8qXXVvWHHSzmMHQ/EhqKL3/ZgRN76go="
        }
      },
      "21": {
        "private": {
          "type": "Buffer",
          "data": "0OV5vl0GqKGYpp299WwlSimR5WhUdUcBgYoUJF40M1w="
        },
        "public": {
          "type": "Buffer",
          "data": "te2W9Jw6BXGdS1eXIzKptoU3+QSKIHzYG8P6C0LcKDI="
        }
      },
      "22": {
        "private": {
          "type": "Buffer",
          "data": "wIqsds6ZD5vQyJMNXZa5y+rJqzunkFVu7qk/criHiGU="
        },
        "public": {
          "type": "Buffer",
          "data": "8w3G/aXMvgxXaks3uuUQPgvAyNjGuXZ43qZF9rYACno="
        }
      },
      "23": {
        "private": {
          "type": "Buffer",
          "data": "yISSvfUhS0g9v04kbLc5sc94qzmYgvFUKUBb00snYWk="
        },
        "public": {
          "type": "Buffer",
          "data": "f6TRaVXukdyc4npbFXr3ALkKrQYfnq4gA4ev90i4ZgA="
        }
      },
      "24": {
        "private": {
          "type": "Buffer",
          "data": "QEIiuW0XFcLjqal1bNj/GNLbpu8x7hIcKb7O0Dl6oX8="
        },
        "public": {
          "type": "Buffer",
          "data": "olCFkyPod1WxTalonxoJ9JAz2Hu0uaNh2+AL7j6o8EU="
        }
      },
      "25": {
        "private": {
          "type": "Buffer",
          "data": "+Cgxydzo1QC6GIHUBRGPqW13WrJWmiemEhEs5bpVaGE="
        },
        "public": {
          "type": "Buffer",
          "data": "Y3YW8hdyntU6kCMG4ksVSlhGrT57eAWrax0isxT/QRM="
        }
      },
      "26": null,
      "27": {
        "private": {
          "type": "Buffer",
          "data": "KDpoyVfTyhuKOA/QrrJcmbozRa7yb2EIcnKiRZrFBlI="
        },
        "public": {
          "type": "Buffer",
          "data": "p3vaCRp2N4JJNVYdki0KQIvkqU+6/NxIlYLAZT3Hu1Q="
        }
      },
      "28": {
        "private": {
          "type": "Buffer",
          "data": "INDFTOA4klMDlMj690QHcP9hMjlmgljrkbnPkT+jP28="
        },
        "public": {
          "type": "Buffer",
          "data": "4LVZ95nnNCI6RqCrKcaMciEzZ/N9joMYF1vShqOV0A0="
        }
      },
      "29": {
        "private": {
          "type": "Buffer",
          "data": "oDKMZRTZl324nJ/tdGAQ5j7U5q9wSF4brfFpg+Fx42s="
        },
        "public": {
          "type": "Buffer",
          "data": "eKzmKld+sknZfn9eqzdofOum57DPGz4hHSggMAYAlQM="
        }
      },
      "30": {
        "private": {
          "type": "Buffer",
          "data": "EKJAwJkLDKC/4nSSBVgh26cGypruOAqrJ/qYvndInU0="
        },
        "public": {
          "type": "Buffer",
          "data": "zO+5295YB1mnWtzIG0/FGVrZXZGnVBOENTsP1hFn43U="
        }
      },
      "31": {
        "private": {
          "type": "Buffer",
          "data": "oNlO5KRnUMUcDO451Pp2PhD8udJs1kOta0ZqvnJjz0s="
        },
        "public": {
          "type": "Buffer",
          "data": "ps0Z6a+DGGv8r4teVIHG09c6Z2qeMaSSeePh7XvZxmc="
        }
      },
      "32": {
        "private": {
          "type": "Buffer",
          "data": "GPsHbQBpqulVOdSsZ8/yZvfNDhZQKFy7c3g60GvEykY="
        },
        "public": {
          "type": "Buffer",
          "data": "F4o8lC3FY/1sXq+apf+l7/LZfRvovBegPl+bxJHh23Y="
        }
      },
      "33": {
        "private": {
          "type": "Buffer",
          "data": "kIwHNpUAlVH2tGsmB5AbPq/F7SLnnyIkMOuZNGeGH0U="
        },
        "public": {
          "type": "Buffer",
          "data": "KdXo9thrCeEtB3X6vyZ+VZfqxa6P9OwXefdXce04DkQ="
        }
      },
      "34": {
        "private": {
          "type": "Buffer",
          "data": "6KQcki2gsSK4GqkdajvU4cFBmU0R6sViTE7Bgyxu+2E="
        },
        "public": {
          "type": "Buffer",
          "data": "iKxg0rGRSwhDWz7BQX1QJ6n8UQLzzPYj8PoiYSjGr3U="
        }
      },
      "35": {
        "private": {
          "type": "Buffer",
          "data": "AHm7nT2g5Jce37fB584+VPEoVW1wXLH9+r627WChn3k="
        },
        "public": {
          "type": "Buffer",
          "data": "FrSSA1W5l0nwFoWgpbVBwzfdXsokTdhq8xw815n9Eis="
        }
      },
      "36": {
        "private": {
          "type": "Buffer",
          "data": "cGS3utR0TSsjMarPLf+em7P/5aQiyLo5qQMaQXB6+Hg="
        },
        "public": {
          "type": "Buffer",
          "data": "Sm/H28WSF5n/gCfh2GoAqKuhdiHk9fpa3kYhXs9Ym0I="
        }
      },
      "37": {
        "private": {
          "type": "Buffer",
          "data": "OM1AM/UB+D2KHybkmK1ltFUYsAJe9tp7gwXD709rPkE="
        },
        "public": {
          "type": "Buffer",
          "data": "4QBEWyIg5gIckuQd8eEV+JhPsQIEFV8OGMbaFu8aEH8="
        }
      },
      "38": {
        "private": {
          "type": "Buffer",
          "data": "ePoUEdFEAz9hcvNbeqmvi7NJxV+5l+169az9a/gqX28="
        },
        "public": {
          "type": "Buffer",
          "data": "WGG5pGhqoeybCSVVGm5Uq6wZZXJGi7nBnutp0yuykGs="
        }
      },
      "39": null,
      "40": {
        "private": {
          "type": "Buffer",
          "data": "SDQFECsKZY19Kg0oCVY3qOUy2/QLl9S1M8bhBMXcCX0="
        },
        "public": {
          "type": "Buffer",
          "data": "NKYdPSV8qHpLB7n+rFjYvWIrweItTezVdySQtcSttnE="
        }
      },
      "41": {
        "private": {
          "type": "Buffer",
          "data": "AD4bSeitd3ZFb9Zfb9hLoGheB10zG9ng82Wa0QkBJWw="
        },
        "public": {
          "type": "Buffer",
          "data": "GnatpK2cfXOYEuenLpxTMwQYpi3j6n9mgQFakxMg2DU="
        }
      },
      "42": {
        "private": {
          "type": "Buffer",
          "data": "2MAAr1J5UzSFo/xgmFif4G0KKEW/FfW+l1ktlu16wko="
        },
        "public": {
          "type": "Buffer",
          "data": "dZh0i6o6Gx8vHAg0F+W9OOFACsDgtoJEl1tIhcUq0F8="
        }
      },
      "43": {
        "private": {
          "type": "Buffer",
          "data": "yL2bpPybIwBwqWo1S+E78wc13cmleggQIYEl+n+c0Uc="
        },
        "public": {
          "type": "Buffer",
          "data": "zqiEBOjLPpAEjf9Li7JS9mo0r6Xg3rUq+NBhjmYoC3o="
        }
      },
      "44": {
        "private": {
          "type": "Buffer",
          "data": "eNj5d12TGORLFMdNUR+iTkmmtfjKAa9Qpv7Gcog4PkU="
        },
        "public": {
          "type": "Buffer",
          "data": "6JzbMDH77YEgW4iBFE+Ynd1N2MHxFJP3BbD8QXOZiQ0="
        }
      },
      "45": {
        "private": {
          "type": "Buffer",
          "data": "oCTB0YSbii7vGZ9eoqnpEHRQq6LFrciRsmVyt8kRxWc="
        },
        "public": {
          "type": "Buffer",
          "data": "BXaZoLeU3OJD8QbvT50D/EFgn3fn1XMqGQLgyUN8MR8="
        }
      },
      "46": {
        "private": {
          "type": "Buffer",
          "data": "sAw1Z3Ovb87UVsoE2fNxMB4w/mlfvybflCbEEQZdbH4="
        },
        "public": {
          "type": "Buffer",
          "data": "dPzCWcy4T3e8vQY/ee5D9BLpEt3l2sYBtYmDqTJtflQ="
        }
      },
      "47": {
        "private": {
          "type": "Buffer",
          "data": "ODWkWJby1EH63bEbSh/+lh+3WlkoYWNiG7BAUK6hQHc="
        },
        "public": {
          "type": "Buffer",
          "data": "bSsfBLYl5pRlzAPIPoxYT4H8uc7B0DSGaEgTlV2CKzo="
        }
      },
      "48": {
        "private": {
          "type": "Buffer",
          "data": "ELnXqzveCRY/5FNF5zm3O7X4+SAcFVqV4VPHxUiQIV4="
        },
        "public": {
          "type": "Buffer",
          "data": "n37HQdsrvn0kNNc882BZjAsU1aZoJbzsp7XMY+AOrBY="
        }
      },
      "49": {
        "private": {
          "type": "Buffer",
          "data": "wNAPCihJ8so8FwoLo+29k8iT33gvDkIYLUd1CByK0FA="
        },
        "public": {
          "type": "Buffer",
          "data": "aaMtjz5r+wwN3b0CMdEX6FDjFUw6Q8NPLLLnkuzHGic="
        }
      },
      "50": {
        "private": {
          "type": "Buffer",
          "data": "QDvo214/l1dCRrdmkXkEQWC41BFPavEAfLIn6ux7xUo="
        },
        "public": {
          "type": "Buffer",
          "data": "hJvlzIz2V6CPMLgkaq1ulv98/FZoFmzGBfx9inBVWS0="
        }
      },
      "51": {
        "private": {
          "type": "Buffer",
          "data": "iPArH7x7NP6Pm+6v2mtnlxCjPUKizFeozUz7jbxJMnc="
        },
        "public": {
          "type": "Buffer",
          "data": "3mtbf5GOKe8g5+hzfigXHPUon/2rY6U2BVnLqApSN1w="
        }
      },
      "52": {
        "private": {
          "type": "Buffer",
          "data": "WGCwIrjMXW6wY7oH4GaTgd49VBcptxlaq/6N5t8xWUo="
        },
        "public": {
          "type": "Buffer",
          "data": "+465dHGgSKc3dqSDzXelkdWuONaZb7ce4iPrSY3wJm4="
        }
      },
      "53": {
        "private": {
          "type": "Buffer",
          "data": "aEulrjVSa5NB9GRq1gLLZIwQE7yRMiUJywHafP7KiUE="
        },
        "public": {
          "type": "Buffer",
          "data": "YswThG9P/3sjkLokMjIV4U4EZvciSlrr7FQX5DBB1Xw="
        }
      },
      "54": {
        "private": {
          "type": "Buffer",
          "data": "eCllCY+peIk6Wmmv0BlH2c68UDP0Q3UmELtGQvMtPUc="
        },
        "public": {
          "type": "Buffer",
          "data": "uqdrbHQji002g2taLsHRVdyJCvCtO/rGgG6IMqfr6G8="
        }
      },
      "55": {
        "private": {
          "type": "Buffer",
          "data": "kB9dIlLXVoKYxzTyGRhUa47jny/muAGHimi5bratBWI="
        },
        "public": {
          "type": "Buffer",
          "data": "9DVx3MEbCRPbCgh0IlDhSzyq3BKLdkVWb4aolrmDKCM="
        }
      },
      "56": {
        "private": {
          "type": "Buffer",
          "data": "iBcOvWyiSIy8gNYwhzPI6mfofDUIkcClJMFe41toUWA="
        },
        "public": {
          "type": "Buffer",
          "data": "C8ngrhNUL/pg/dHxFKS8kQHBCFwP/reaUUa+jpKPdGw="
        }
      },
      "57": {
        "private": {
          "type": "Buffer",
          "data": "OMycWO9UQgZsbS7iV71TTukAgJugyCQcZozVsvv460U="
        },
        "public": {
          "type": "Buffer",
          "data": "TWrUWaOJJtgccDQ/1wVnMklm9XSvvXcomQbn2ZO0iWU="
        }
      },
      "58": {
        "private": {
          "type": "Buffer",
          "data": "+CFVt7TbfeA6cnFyW3KdNZAxrZ6DUdKVzBuq+uYmgmM="
        },
        "public": {
          "type": "Buffer",
          "data": "Uf/4FcB9NyGF0ArplM2adPUVMin6v+aEFh7md3l6plk="
        }
      },
      "59": {
        "private": {
          "type": "Buffer",
          "data": "YDyBoYKC2BpalTLVW1zQyoNio7P2Oa8N9FdJUCSIMUs="
        },
        "public": {
          "type": "Buffer",
          "data": "+qYniQnK0L6ptcW7/EsswQM7yCEdh+iBeW0WcQHI4D0="
        }
      },
      "60": {
        "private": {
          "type": "Buffer",
          "data": "AO1jyjS+y9ZVdF2SNvaoN7lem1bNPh/ec9gj9ZUsRHI="
        },
        "public": {
          "type": "Buffer",
          "data": "6B2T4+tAfLx6mDKuveFwjNC3Aznfgc5uQWLtWorbDQs="
        }
      },
      "61": {
        "private": {
          "type": "Buffer",
          "data": "wOgP0EMDgc0KkYKhteGXusfVKwBeIDfZGVuD3Jo3OGk="
        },
        "public": {
          "type": "Buffer",
          "data": "vI1kItbiaq5oOWXezBOppi1Y0jVjQhEzNEhzv3PTOwM="
        }
      },
      "62": {
        "private": {
          "type": "Buffer",
          "data": "EIld08TbzGUa1EcFMYe2MVXV1yQgVElUXu0oKp8DGn0="
        },
        "public": {
          "type": "Buffer",
          "data": "rx8VycGEQNebgicYrTZ4g7M0gREjFsJRais2yc48bHo="
        }
      }
    },
    "sessions": {
      "6281998199848.0": {
        "_sessions": {
          "BVTA7F/WHhZJbGyspfQQKLW15sbLvhWZelHhGXujeB8t": {
            "registrationId": 318384051,
            "currentRatchet": {
              "ephemeralKeyPair": {
                "pubKey": "BZPHrTQoxsAc52BWqDy5PwyLlR2FYKAwW0aDh3AvOt5j",
                "privKey": "oHtj5x/U+ByJlbTq3Yr9Obl09HAsokjrmmm7Glyur2o="
              },
              "lastRemoteEphemeralKey": "BbLy+JAN/Ueix0Kpv8nzH+PWINIgbnx+fwfG/ITKBgIr",
              "previousCounter": 1,
              "rootKey": "tKGEbJJXe3CD9spkvD7Pm8Pzx0bq389qw/MSJc9Bgqw="
            },
            "indexInfo": {
              "baseKey": "BVTA7F/WHhZJbGyspfQQKLW15sbLvhWZelHhGXujeB8t",
              "baseKeyType": 2,
              "closed": 1673264335721,
              "used": 1673225518169,
              "created": 1673225448988,
              "remoteIdentityKey": "BX2WhyytcdHc0Pw/DzMIDoRPlgPLEyiOsIK3p/51Q556"
            },
            "_chains": {
              "BYWNCU+d0eM5v7Wcou9/zJo83ou/iCwLVJtXkGU8UC4K": {
                "chainKey": {
                  "counter": 9
                },
                "chainType": 2,
                "messageKeys": {}
              },
              "BYK4gj/Hu1Iil6ICebPUViMfzUB5AH0xytMSl0GpqUx3": {
                "chainKey": {
                  "counter": 3
                },
                "chainType": 2,
                "messageKeys": {}
              },
              "BbLy+JAN/Ueix0Kpv8nzH+PWINIgbnx+fwfG/ITKBgIr": {
                "chainKey": {
                  "counter": 0,
                  "key": "ElZ20M2myJGUlxZMzH061r4Md/AflC61BvyQYvhpUsQ="
                },
                "chainType": 2,
                "messageKeys": {}
              },
              "BZPHrTQoxsAc52BWqDy5PwyLlR2FYKAwW0aDh3AvOt5j": {
                "chainKey": {
                  "counter": -1,
                  "key": "M4FBvSrQ3dz952S7JBapBGzve2+j7dY2ZmA7kSZmf3U="
                },
                "chainType": 1,
                "messageKeys": {}
              }
            }
          },
          "BetE0f9ux7LBeRWXSL7ogaYD8+UUw9DKx3CSIWc9NzNi": {
            "registrationId": 318384051,
            "currentRatchet": {
              "ephemeralKeyPair": {
                "pubKey": "BbksKTLaFyoY08TcZqnPXY9YMCdWnECaJxU9nlaOK+cw",
                "privKey": "2Gs2iSvvxlW49pt0EgeLBwV2pq0zKOOYjKJ3KUpcB2Y="
              },
              "lastRemoteEphemeralKey": "BeapTQuO7R+ITbKbyzrHmKxlDweDLzMi+huW19nhJM9B",
              "previousCounter": 0,
              "rootKey": "34jsyea8Q2IpxAHbOneXmtbwqf5lJ1t4iXglz8YjSfo="
            },
            "indexInfo": {
              "baseKey": "BetE0f9ux7LBeRWXSL7ogaYD8+UUw9DKx3CSIWc9NzNi",
              "baseKeyType": 2,
              "closed": -1,
              "used": 1673264335761,
              "created": 1673264335761,
              "remoteIdentityKey": "BX2WhyytcdHc0Pw/DzMIDoRPlgPLEyiOsIK3p/51Q556"
            },
            "_chains": {
              "BeapTQuO7R+ITbKbyzrHmKxlDweDLzMi+huW19nhJM9B": {
                "chainKey": {
                  "counter": 0,
                  "key": "PctMwwReA/gmaL+4kQYoRCe+XLi8oPE1xhjFPgNGjsw="
                },
                "chainType": 2,
                "messageKeys": {}
              },
              "BbksKTLaFyoY08TcZqnPXY9YMCdWnECaJxU9nlaOK+cw": {
                "chainKey": {
                  "counter": -1,
                  "key": "jBCfvPQZCSKyML7DGsoxPb9CkI/BWQHQdXuhJva+AaE="
                },
                "chainType": 1,
                "messageKeys": {}
              }
            }
          }
        },
        "version": "v1"
      },
      "6282125718289.0": {
        "_sessions": {
          "Behqbi3jy6b/SuMKlN/K1MWNJyH0u8G97GtO27/MBIIA": {
            "registrationId": 179280205,
            "currentRatchet": {
              "ephemeralKeyPair": {
                "pubKey": "BdQ0oxWrr45yWPVRmeRD2IZDx3yPSjc6fIUE0LRsJXR6",
                "privKey": "YGA2it55eumDdlLYSE8FA+QfFlVORPN150ozbC+gL3c="
              },
              "lastRemoteEphemeralKey": "BTu1nu+9CWh/g91VcV9rSZXbKmiPl4fVTEtuPvD5tLdl",
              "previousCounter": 0,
              "rootKey": "xYm0NzjWHwlQM2RrxYN66j/X5FjyB0Hlv7duF1n1HLs="
            },
            "indexInfo": {
              "baseKey": "Behqbi3jy6b/SuMKlN/K1MWNJyH0u8G97GtO27/MBIIA",
              "baseKeyType": 2,
              "closed": -1,
              "used": 1673225454117,
              "created": 1673225454117,
              "remoteIdentityKey": "BQ+CfMoPirM0dXV4gDTmPOsPtE1cXm9s/+PlMMNEu6Y0"
            },
            "_chains": {
              "BTu1nu+9CWh/g91VcV9rSZXbKmiPl4fVTEtuPvD5tLdl": {
                "chainKey": {
                  "counter": 0,
                  "key": "dq4E+LrsqapaOrVEk8jxy+nGjgVuhaIGCotkCgQpEkg="
                },
                "chainType": 2,
                "messageKeys": {}
              },
              "BdQ0oxWrr45yWPVRmeRD2IZDx3yPSjc6fIUE0LRsJXR6": {
                "chainKey": {
                  "counter": -1,
                  "key": "FmS7N1q7PC+fp+IKr02nkADWPmH/5LNfKCiaDL1Klfc="
                },
                "chainType": 1,
                "messageKeys": {}
              }
            }
          }
        },
        "version": "v1"
      },
      "6281938830020.0": {
        "_sessions": {
          "BcZL4/8vgTdUaM5DNV45QC0Ti7raBMwPCckCXtHIcqJw": {
            "registrationId": 1887230686,
            "currentRatchet": {
              "ephemeralKeyPair": {
                "pubKey": "BfPl+PQMQoh/XcYx/3+CVRlc1qWf379AFfzVJdxrhqJ/",
                "privKey": "YLoNdY39YAPvHMs08FxRD70T7STG/3EYGWCWuWCobEs="
              },
              "lastRemoteEphemeralKey": "BYPIjKuz852aZqHdWvF59I++cbIXhaIclVvpty3TQHgU",
              "previousCounter": 1,
              "rootKey": "9rKkQ3e/nUWSWQ845CE8MuWufxY6zYuaPS2gBkF+G/k="
            },
            "indexInfo": {
              "baseKey": "BcZL4/8vgTdUaM5DNV45QC0Ti7raBMwPCckCXtHIcqJw",
              "baseKeyType": 2,
              "closed": -1,
              "used": 1673225506839,
              "created": 1673225465661,
              "remoteIdentityKey": "BY3tS2d4/Sv0N8HM/tEwODCs1KJZtZKvS6YXtIe4FMQ0"
            },
            "_chains": {
              "BX759WEQIwcxMSMezJpLCS7c/cMz3e9WFFZ5/70TVhgS": {
                "chainKey": {
                  "counter": 3
                },
                "chainType": 2,
                "messageKeys": {}
              },
              "BYPIjKuz852aZqHdWvF59I++cbIXhaIclVvpty3TQHgU": {
                "chainKey": {
                  "counter": 2,
                  "key": "Cl4IPXoWuZ+Lc/m6qGZjFtOoQeGmCmQfe5rkvJ2RyI4="
                },
                "chainType": 2,
                "messageKeys": {}
              },
              "BfPl+PQMQoh/XcYx/3+CVRlc1qWf379AFfzVJdxrhqJ/": {
                "chainKey": {
                  "counter": 1,
                  "key": "1EPn/2gpunheFNOgs/bxgxdxeOdy5iVmakMBHMEVcEc="
                },
                "chainType": 1,
                "messageKeys": {}
              }
            }
          }
        },
        "version": "v1"
      },
      "6283159644910.0": {
        "_sessions": {
          "Baqx0RV2iz2zj85a3kxrLx1AUTa66C3/pp0GD+4pncga": {
            "registrationId": 118821923,
            "currentRatchet": {
              "ephemeralKeyPair": {
                "pubKey": "BWTM1mB2smeSAW+gUFdvgkbiP1KNq76PtiL+W2otHiMp",
                "privKey": "ePGHKFzo03HHHabcjTTMkqTwCO1MVauS4Dx59JAvBXo="
              },
              "lastRemoteEphemeralKey": "BaGAOxXq+tCMxwACp6kbyZEezEcSH0LnTncR+6Hfjfh9",
              "previousCounter": 0,
              "rootKey": "znT9GvqvcokT0eTcSgdIYa765VLHSQ5f6Zc0N9amR8Y="
            },
            "indexInfo": {
              "baseKey": "Baqx0RV2iz2zj85a3kxrLx1AUTa66C3/pp0GD+4pncga",
              "baseKeyType": 2,
              "closed": -1,
              "used": 1673225480124,
              "created": 1673225480124,
              "remoteIdentityKey": "BQuC9VOCzeEpKfgJvkQMryEHjBKihIdUk3E31uniAtkM"
            },
            "_chains": {
              "BaGAOxXq+tCMxwACp6kbyZEezEcSH0LnTncR+6Hfjfh9": {
                "chainKey": {
                  "counter": 0,
                  "key": "zryMTa3N8EiVhuMBjLxeMrOWCcizTyj90IN0toqrL8w="
                },
                "chainType": 2,
                "messageKeys": {}
              },
              "BWTM1mB2smeSAW+gUFdvgkbiP1KNq76PtiL+W2otHiMp": {
                "chainKey": {
                  "counter": -1,
                  "key": "8XhsW1dObEtz8B6Ex/at9k9unXBzci0OvvChCklTzAU="
                },
                "chainType": 1,
                "messageKeys": {}
              }
            }
          }
        },
        "version": "v1"
      },
      "62895329406541.0": {
        "_sessions": {
          "BcTKgwuYVZfoANGApzMnWy1V5sMXolcJqgfJSMd+QJlM": {
            "registrationId": 1260982416,
            "currentRatchet": {
              "ephemeralKeyPair": {
                "pubKey": "BcqDtR+Gkuxx9lC1FFJP3yFMcoHPBSEt28MMZ1VzoQNc",
                "privKey": "+L3t6F9awYhuA9eDFSJWtxX/O7ZyBIHlKrdjP9K3EnI="
              },
              "lastRemoteEphemeralKey": "BSVXMRJ4HJPWtcGVlKqUZCpJWyyvqtfXy1Ic2JDinUZB",
              "previousCounter": 0,
              "rootKey": "NdBk8242qE/azIrI6LWobQOExsnSVL1NQ4iIyJsch48="
            },
            "indexInfo": {
              "baseKey": "BcTKgwuYVZfoANGApzMnWy1V5sMXolcJqgfJSMd+QJlM",
              "baseKeyType": 2,
              "closed": -1,
              "used": 1673225504394,
              "created": 1673225504394,
              "remoteIdentityKey": "BQFfjAN+aCtHaI+ZkH0uhq8eKdFsu3B8DCneyyuM6Z8T"
            },
            "_chains": {
              "BSVXMRJ4HJPWtcGVlKqUZCpJWyyvqtfXy1Ic2JDinUZB": {
                "chainKey": {
                  "counter": 0,
                  "key": "/4+s4urtKzgut5INY2x7NXLpEzJuF8NAKgCO5lDug6E="
                },
                "chainType": 2,
                "messageKeys": {}
              },
              "BcqDtR+Gkuxx9lC1FFJP3yFMcoHPBSEt28MMZ1VzoQNc": {
                "chainKey": {
                  "counter": -1,
                  "key": "lQpxAHExN/i8L0YhzbWNqeI0Uf3TWbYIZHdiWfOM+7Q="
                },
                "chainType": 1,
                "messageKeys": {}
              }
            }
          }
        },
        "version": "v1"
      }
    },
    "appStateSyncKeys": {
      "AAAAAJ7+": {
        "keyData": "0WPValyKq/xcprhnFLA+gwz/bqFvh6zZ+pJc4QXqpUc=",
        "fingerprint": {
          "rawId": 892823864,
          "currentIndex": 1,
          "deviceIndexes": [
            0,
            1
          ]
        },
        "timestamp": "1673225448586"
      }
    },
    "appStateVersions": {
      "critical_block": {
        "version": 1,
        "hash": {
          "type": "Buffer",
          "data": "abE0y+JfCMKBj+5sOBib0vAV3iSgqFhkdLXwuKLdV2S2LMahCr4goDpmLpunCeBKyRV0Mf7Z8G675NOtgi0pcNKEu1mpvV3fpRHwKF47LTD6PCm6EnsNk4T2btH7vfMOP7BCy+YQnrN9mDxyYExZ62zgFNPx843IdARxwF9ng2k="
        },
        "indexValueMap": {
          "xsE0wRUpROq8hPdzbVcRJIonpFPyhZQwVVZzwx1+YTM=": {
            "valueMac": {
              "type": "Buffer",
              "data": "hTmGNcnbeocQVVCovuxCXdM1WpctlD7VGsrvgXrWy+g="
            }
          },
          "h1bwUJlbG3pLGLDjSO3BxoxcwhEHnsGAGtJvxSOTHFQ=": {
            "valueMac": {
              "type": "Buffer",
              "data": "p+HFhvkXO47ruvbWbi6GgRLqRp3nSFENOmC2+jI9SP0="
            }
          }
        }
      },
      "regular": {
        "version": 1,
        "hash": {
          "type": "Buffer",
          "data": "o+PIDt/n6eXdHfV3e4w+fQOm9k6xSz/q/yHUxqZ0vv8vvB4G25Sh3j6kjqZHy/mBPihtg/E3VpbRWHLKxB7aEjR2cmgh5hCeBB2XUM8TbqbNWwPxWGlOF/U06mvV+EyTr9EWmfQ6e8zpphBU9DGgFFcDjjnqi9S9B6dYufDqlH8="
        },
        "indexValueMap": {
          "GjYu74FZabD1Uvd4Prt2oQYsM0K52tDBWcEtP6qwcEs=": {
            "valueMac": {
              "type": "Buffer",
              "data": "XKYuOnBwSIhTMhfwtHUmlP5/3KFF21UvBouow98UOuI="
            }
          }
        }
      },
      "critical_unblock_low": {
        "version": 1,
        "hash": {
          "type": "Buffer",
          "data": "oYVsTyztB7yty3km8pXjmb6xzzyLh1XuU1C/W57BLihlDEvNWEC2cH5qxOXq+iyIBzkYyESbf2/NZLo+aw64Zelhdk2RjCosiVwnDor6DTxkFIUbE/7Eon+GA8/jZFCovNr7E1ZYywInB1cnf+JJI5Dqw/psvEKcIa7sr6xR3Ls="
        },
        "indexValueMap": {
          "mWjQCogxbsZ5MnjDVMkLYzpl5lN5bqklWVZ+xnUNedI=": {
            "valueMac": {
              "type": "Buffer",
              "data": "25UDGI0A14qrbzS0hKOGnzsv0QDy2D+h3+JBds58yu8="
            }
          },
          "+0afAzcznTN73jkoc813GbR0JIKn7m7/+zQLKKBxMiI=": {
            "valueMac": {
              "type": "Buffer",
              "data": "9KtCJ2Ve+pbqk+IeeEdtswjHZBa90xv9J+7o4+mtOHA="
            }
          },
          "q+6vii0k15b/+toBjfrqE9jtnYfyxPh5eWfIbPsPIVA=": {
            "valueMac": {
              "type": "Buffer",
              "data": "VcfdqN20ovvQJIaF2JIMk9YtirxMfcSmcQABeHpvrt8="
            }
          },
          "FjR3RuQIxOBTieCzqBN7wLhHH1nAhdke6kyOX1bhTns=": {
            "valueMac": {
              "type": "Buffer",
              "data": "QzaNSmR7IqjSFGRxxMgTByALvuGZhA2POApFFJubkpY="
            }
          },
          "YBd1MUmasEgFqzrLrQTDV5DZnGDLOzkdtqjrUzAcMe4=": {
            "valueMac": {
              "type": "Buffer",
              "data": "dpB2Nuwnma+xFviUFDUvBlcbAW8KikkkjPCRe/w3dVI="
            }
          },
          "QEshOX4NQSg/ylzF1scc0TFDHy7Y18h6nuM1XZaiXpo=": {
            "valueMac": {
              "type": "Buffer",
              "data": "g5Qs/f8rkjJGE92RLc/xH1JBJkNQaNf13QdiAoB0mbY="
            }
          },
          "jV39WAXmwqAjhFJsag808h0QDFcruBU5U19Kz4r+Hio=": {
            "valueMac": {
              "type": "Buffer",
              "data": "NPA2/1OTR/P0sTn3mztW4ln3t15I+bQCI8YLSKjePe0="
            }
          },
          "jhIieywm2GJugdFcfigcfla7NhEBAG9Ls7oXjp5SY3w=": {
            "valueMac": {
              "type": "Buffer",
              "data": "Xci70cKfsBgXlvTLAUyN8fIJhjNk7H0Nnf6VVtcI0go="
            }
          },
          "mpg3CctxsyaJaDf9+msaYkyhuls7ily6Gmc+rx6e1cA=": {
            "valueMac": {
              "type": "Buffer",
              "data": "21QlR9Yn0IrXTLLR3EvHzcXS3L61mLMRi553VaLfSzI="
            }
          },
          "ImzA91lQz/5/o01dTjh+ldcfZcvhreTQiNUs7PQPVi8=": {
            "valueMac": {
              "type": "Buffer",
              "data": "8LfXPUDj62C82y8k7rjwkBIOVNVYVzUFDOOc7cd2gBE="
            }
          },
          "rrhROjwXwC+sGquDkKA2t1WBHE2BemwxZoCSm4ZKy3s=": {
            "valueMac": {
              "type": "Buffer",
              "data": "Atz0LCxN9XG9CNLXiLdoUtNLvyOC6OMPPuqlDFGe0kc="
            }
          },
          "mCfOjX7o3vFacVKaXRs0cwZPN2434rPWODxtX9qtr6c=": {
            "valueMac": {
              "type": "Buffer",
              "data": "8y9zZ60e5Nurk9/0UDLcuvZ4s6WsrUOZtsA4OuYNxNw="
            }
          },
          "jKnP4zZp839Gz++I2qV2rLMKQlNuVFH0OpDMzpQtgQU=": {
            "valueMac": {
              "type": "Buffer",
              "data": "/GD7kaE4Sa8+V4J6ckvjH5yX3O/CI2RmUiOzNHtXioU="
            }
          },
          "detH/KUNUxKV+hElEKi2OGrmliwJkvofs51ORVhhhWs=": {
            "valueMac": {
              "type": "Buffer",
              "data": "yZomj6JSqwMjg+xRtj42sspQKY4humfEUPFuYArUHZg="
            }
          },
          "NO6AV+rZZW4HkQAUTRscPY2dSLHLzNjyi2dkGGZy+/w=": {
            "valueMac": {
              "type": "Buffer",
              "data": "MsOcxRFjXbKRtzmpTJjxR35WeqSqYoY4pbwQkgFVzRI="
            }
          },
          "PeMbwbF7aDniWV6WI2Nyh9BH1tk+jLM0SGUuNnmyeAQ=": {
            "valueMac": {
              "type": "Buffer",
              "data": "5EVhBYUV0+OmV0myZsvuYpf5ocooB+A+F5smt5iwd2c="
            }
          },
          "NUyssMX0Dc0v5z85k2hbDgcAGyWc0YfcKkSC/o/p9gc=": {
            "valueMac": {
              "type": "Buffer",
              "data": "f46RcxU8ecxfUUeC5LyYPHk9YOReeokISm0dRSvGU+M="
            }
          },
          "Dm8jk/WDxXx9B65UnmxBC4GLcdPPbUXyejp5ZQbmjCg=": {
            "valueMac": {
              "type": "Buffer",
              "data": "ZRI4MMf/bchRiYe2vV1LHtM9RxPc+vwakVRoYMmyo5Y="
            }
          },
          "N24dgDwXGz7yj0qqDS8KTUUItkegoz1OTdmzC4xIx6Y=": {
            "valueMac": {
              "type": "Buffer",
              "data": "Rc8seNjCbGH6CvL32ImXCEzlSq5wRCWqgQ6xEdlJ618="
            }
          },
          "kgHK8aOj5YpnCmKcAhgnlnlOX9eVGSWP2NoSrfcCTxs=": {
            "valueMac": {
              "type": "Buffer",
              "data": "8ANZnj4jeEDxpX884/MUKlGa9OtvkRzG6esggHvo5Ew="
            }
          },
          "V36yTg7qBBxx6GAXqn8FTpbFsci/TBZ0D8yaa/XoxEc=": {
            "valueMac": {
              "type": "Buffer",
              "data": "l7RlY2qmOaW+Ip2R+FwYTHv4gHkuTH0alsUbry/Lsgw="
            }
          },
          "SKlBY4XUfpekbZYh6upF+wruYsl1vA8FxUIH/rTydaw=": {
            "valueMac": {
              "type": "Buffer",
              "data": "RD0iJcA5fgGP7h87O4rnIuvnjnJY1mCnRtJ0rvQBZnk="
            }
          },
          "dMLCID/cLVvVvLTuOgeEj5aSVha8h5Sim/OGcAZc5lE=": {
            "valueMac": {
              "type": "Buffer",
              "data": "Zb7uuNQhjMJ+dOLsAHJI62eP6wpFUpaoD6NhaBvDFkQ="
            }
          },
          "QuAYLwmTUlAspM0PTxg7/mIOzsdkCMjE662Aytxzuig=": {
            "valueMac": {
              "type": "Buffer",
              "data": "Uk3AX6pdEixJo6OqPHsh3i2zLwa+dvjeaDdchYQpcbA="
            }
          },
          "wyowwjPW4Iza68+H+/eVedmTeAEf8BVGT7+h8rw5kXw=": {
            "valueMac": {
              "type": "Buffer",
              "data": "QVHrxpGvrkJ7OtvU7h2Vx4mNyUBmH+hpyuAWPkYfPRI="
            }
          },
          "XNxHbL9IW1d4kiMLr+0xZDusEjfMr4atwmF9Q756rf4=": {
            "valueMac": {
              "type": "Buffer",
              "data": "ui557Hm3oq/sVNvEQKxOtencCZQ4OdL/oDPzrl6gskE="
            }
          },
          "/qVGpAHw2480r+s1/TMea9ouJjGz9Xu9Fnja8tbmH3w=": {
            "valueMac": {
              "type": "Buffer",
              "data": "rDI03VGeBcBWbBco1hQmqdf0dtR6Xg1b/I46zm4lUJY="
            }
          },
          "vQZXjAa5gi6HlTRp70Yf/dkHYTIc6SUUH7j2ehIqtrQ=": {
            "valueMac": {
              "type": "Buffer",
              "data": "LE5LYSNWpqJOZqazFIWC0oTLkPknGFQpgLk186n7YGI="
            }
          },
          "gDRyfO2sipM8FykiAdmM5woxVjaeoJbUY8G0C03AqbE=": {
            "valueMac": {
              "type": "Buffer",
              "data": "zvNA56yklIaX6EyGjxBNs5DMOh0WNCOhjRlaD6QbTcc="
            }
          },
          "Q0jILTGQ/WmNXu2F8RBIRrnHCJcuqF6nVUTnvIxrRoM=": {
            "valueMac": {
              "type": "Buffer",
              "data": "6Q0uVH6zfJS13xSosPpk2Y/x14GYWKpEuaPfmlLRjn8="
            }
          },
          "rOGAaqmWdlHJp0wVwnDzZ4lj69bAykG5zp8OOqkFOsk=": {
            "valueMac": {
              "type": "Buffer",
              "data": "QKQxar9+NaE5fMkiGd+7dYtJbOCJQysrtMBbKwqWskQ="
            }
          },
          "IgClXNmdTiIC+NR151Wlx9gF/c5b5uF4+hNtVILNKQ4=": {
            "valueMac": {
              "type": "Buffer",
              "data": "3xZSNu9cslcGoRBBMc7e4lYGFHoSC0bd/BN5aChLXUQ="
            }
          },
          "Mcm9TJ/MfY2oyBwiUOMG2OGLMZ1cVCrE0tSmLWxesPY=": {
            "valueMac": {
              "type": "Buffer",
              "data": "mnK0itS1jTtkxLEy0EmXzABvDSX/wWXxO3UzgLMN5qU="
            }
          },
          "ehRLZU+g0zw+9UsZo0a0VElKqI+x5tQjC7jszeOrl2w=": {
            "valueMac": {
              "type": "Buffer",
              "data": "JOg0ilQDYqTIsohepOtiFKxmduZmwcgCT1mg4bTr+D4="
            }
          },
          "EbCGe/dYD41OFlaP4oSXraT+dM5oahXor5wFxHR2CF8=": {
            "valueMac": {
              "type": "Buffer",
              "data": "Wo/NbYIqnrGlwF1mBQnuXy8BPwMOmhVpJ/EGELELnNg="
            }
          },
          "YLi33/ULys3hf+1ONnvo9HQCAABCNvw41z09A6x6XWw=": {
            "valueMac": {
              "type": "Buffer",
              "data": "gTmcQh1VzPkvvuE9jHMh07IK+g8SD/6VvoG42GQ2tfY="
            }
          },
          "ljmuoHFVGGiGrUEQr/AC7ZeOoSad7JNFjpl4Si3YHHo=": {
            "valueMac": {
              "type": "Buffer",
              "data": "W2SJiuKuQ8uOVVOJ//K8MESHa1Yk6LqlfbH6FNZzNkU="
            }
          },
          "kRwMp01OvlD7yiEThh3W6xfsjRmErS/MB+ndgNIh54w=": {
            "valueMac": {
              "type": "Buffer",
              "data": "DOHiYb+K+WbBmhgNhCtA4PTqt1y12T+xyQoQgThjuv8="
            }
          },
          "Yh81uELoH1FsuwNtVVWYMhz1fzwF9TXIo/MEfADzcVA=": {
            "valueMac": {
              "type": "Buffer",
              "data": "f95eqhQHHTtnL1d9ArnW4X7l0V1OluyT2iC0BSBsTDY="
            }
          },
          "l04+CT5eJ+28aQPGbX1HN8n1mxxcDJxOmC5wlsBadS0=": {
            "valueMac": {
              "type": "Buffer",
              "data": "StEvJ0mgQOZ1HpOp2pw+MCZwzuRaic6mLzkFrlpqtFs="
            }
          },
          "iX2AlwLlHR1da7lQJ7pD7FLKeSSF5OkTu60VYim0RP4=": {
            "valueMac": {
              "type": "Buffer",
              "data": "HqYDLiUVB0UJU3H7fSjl9+Zn//PpgXIM7Xab5t0V8GE="
            }
          },
          "zK2SM/Cf7ftJfSvPT5qzlNzWo89hg056DDVQvpMvmtg=": {
            "valueMac": {
              "type": "Buffer",
              "data": "34qQy6MzUb5nsVrCxzlX3yzZ1+V4e9WQlhOmjFmAGgI="
            }
          },
          "+aBrFF5uXj/6dzgL7pAAKpK5g1UyGDN//LONGFd4ci4=": {
            "valueMac": {
              "type": "Buffer",
              "data": "POQk/4S2VF+HIB06FtYDCaHI3HbDqtdjNdWnRs0SjoA="
            }
          },
          "gStk0tqSV0ZK/d3jkYBFrTyRthDQA709bvhp7YNrSSU=": {
            "valueMac": {
              "type": "Buffer",
              "data": "qHhTixCGcDcMECmWpU2hi4S9P4CETtlCV5FvaXjb0vM="
            }
          },
          "AMlP1X4lLkq8HULvgqgDMzhMWb75T8pYxcLBbooy3so=": {
            "valueMac": {
              "type": "Buffer",
              "data": "UkSb5bM2+hdjVYkXbWeeUxkImTBggE3GtB66BaeMiQQ="
            }
          },
          "0Em/BLLJuHY3oU3MJIpEHdJyn9BpTD+7N/hnA5+KOck=": {
            "valueMac": {
              "type": "Buffer",
              "data": "1Rme++V3CJs9Ya7xCXbZkD4rI0aMs+ocQWDoZw7M1Cg="
            }
          },
          "+ew5UHaDdl0EgBuEpygu1KH4wW53mVO1SueFf/BXb5g=": {
            "valueMac": {
              "type": "Buffer",
              "data": "7o+J1HHPUwxnP6Z/RuOcCjMuIpirMQaBi9EY2JRWkrY="
            }
          },
          "XtcYLsmjOYMk43sooooJrQYLl8Lz4J5UCOKTF4Ss4qc=": {
            "valueMac": {
              "type": "Buffer",
              "data": "Gd7a3yv4pInRxCTvquEK9Y0XmS45WXF3YdOpvEU9IuA="
            }
          },
          "PG9ioDV7Cw5xQqum1CDdN+DPMj17uPVCSX+b3Ew8VLE=": {
            "valueMac": {
              "type": "Buffer",
              "data": "pcBnS3XO3WE7q+r6hgCbjroC0+sAjDFobY7Gzh8HmtM="
            }
          },
          "zBW0aHo+3Ha9Sik/YiXZSmfRoX20L5bFCRkzh6I64gg=": {
            "valueMac": {
              "type": "Buffer",
              "data": "yM6hrSDigq8e5utsgwc/f3CZ62TYI4IS0lyE+2Epe6g="
            }
          },
          "PnNDtO3AM2e6NVx5AeR8LAbUFuHC6Nd/DqCvhq2O5fQ=": {
            "valueMac": {
              "type": "Buffer",
              "data": "nlevpikQJSg71N2X29AHas5JRpaAjm7Yph4YdBX0ihQ="
            }
          },
          "LNXdBUT2gFxyguIq6WN4iyDIqOR2m2Ah5G9zV92IN8E=": {
            "valueMac": {
              "type": "Buffer",
              "data": "p45GY+QqIkrTkeJo9NgNNW7M2UaNewMR11WcCthci6c="
            }
          },
          "y9Ds8jSpshi454M1g/TNtvZA/MpT/QeJzNsgKC9aClM=": {
            "valueMac": {
              "type": "Buffer",
              "data": "WdN5qJTn/XtGmgsynjl4+HvtWWC2Sc40f3zX9YlzsJ0="
            }
          },
          "xXKoRhi5iYM08QtCKCNNlUKx87AySZodroyKDbLyqFA=": {
            "valueMac": {
              "type": "Buffer",
              "data": "NqeZFq3JT8lL0QbFwU3WtrKGTSA+7BhI9IbVwa60cSo="
            }
          },
          "WlWith6GvwGwil/DY2xlQpXHC6aS5uK8KH5NZt7VcFw=": {
            "valueMac": {
              "type": "Buffer",
              "data": "T0c7zU+NlJWuYIYfMEDjT9XnOovVRsiQKLJQy5DDNhw="
            }
          },
          "4r7XPd8mIx8Nv6lTHkgSyB0JSKmIvUlGe6s9rxNJoMQ=": {
            "valueMac": {
              "type": "Buffer",
              "data": "smjnCBUoODZ/kZpG8u+L0iBnOMrtJcYMw/98ZrJfrCE="
            }
          },
          "5ChNsXY5CpRERPrDEgQqHns7oOv4nLF6kC6H+l5EcmM=": {
            "valueMac": {
              "type": "Buffer",
              "data": "kg4mnZeFwu8vMeX7HjBIWTzwfHxJQuUaZjQPpjH2fSI="
            }
          },
          "gNG+aljKfCZ2WbBBH7eer7zroG+sxQgBigWxa6PQAJE=": {
            "valueMac": {
              "type": "Buffer",
              "data": "jhR0HCAbTO9c63a/PkLtFqNDt3WBpLQShLg/DcnEOOw="
            }
          },
          "zGmhTv11WjJsG34klqUnUXqQroxlsfm4Q4JzFTVbvzE=": {
            "valueMac": {
              "type": "Buffer",
              "data": "/ssEJgQPLRWw8ZedppVtZR3dWBDOsY4nYOZefApPkfk="
            }
          },
          "nvv2NlkJkHarl73Za63Ygxm8ehTudCLIG7cfUvF9T1k=": {
            "valueMac": {
              "type": "Buffer",
              "data": "4F/wGmTPdSLlDq9cBCSlH/BggVOi2fZBnwBEDemjLZM="
            }
          },
          "XmUJxt6O6+SxQQCLI7CYTBk+DJIg2mbVrLPj+qn3h9U=": {
            "valueMac": {
              "type": "Buffer",
              "data": "2xJpfYM4Iw3JMchJ23GF9x+BVuCx1+qLbzi+seaY29g="
            }
          },
          "tCeRiO7+AFU5nktRDVQUYsc+BMq691M2IlzHjVsrT1Y=": {
            "valueMac": {
              "type": "Buffer",
              "data": "V/d92i5gbdCdUMkGyuSU46MGKqbcL2+dwNO47vaHGwM="
            }
          },
          "Wum2dekqKmiSH12rfreUncJH+KKQBPgtcvOWChMOxvQ=": {
            "valueMac": {
              "type": "Buffer",
              "data": "sA+2WaYFmXDUk+uKkXRmSfoUCuG9YiuYpVjOe6uT3LI="
            }
          },
          "oXWjYmBOXBtudH6WSzIBah5t9fC2wBV/pRuNoKAM5uQ=": {
            "valueMac": {
              "type": "Buffer",
              "data": "nuW2qffNuj/eogKjVfjL/wnCntYd6qVIuDDE0yYylqE="
            }
          },
          "P6Yb3hR3Yc241FeVay5DPX6jHx4ENZnCQ9B+MPPbbX0=": {
            "valueMac": {
              "type": "Buffer",
              "data": "A6K3mLzBkxn++MHPc/9lLX+DKSz6U6umF3vw6NNAqY4="
            }
          },
          "XhokYWT/Tw+cBWAGUT3EZsn3EtPAB6wrnh4uWXuV1Wk=": {
            "valueMac": {
              "type": "Buffer",
              "data": "psdHDycZTYVtJWFumun4nzfp+6g6eOkXTfsYuv4SX7A="
            }
          },
          "uNC2sQ9kakD7O5R9BvRZQy8q5mY+lxvtlCT0+1kDuc8=": {
            "valueMac": {
              "type": "Buffer",
              "data": "Q85IoSANiCMirErtou2XKYROnhPp5f766pW8kGVpx5o="
            }
          },
          "1IxbWPjlTB0B7ajiIzmAzgXqWU2MR1TZGcHCpbf2q5w=": {
            "valueMac": {
              "type": "Buffer",
              "data": "yjKrTt4i0jax04FcmatD5taCH4dhS+nDKuaIZB1Jb2E="
            }
          },
          "uEoutNH6OO7CH7Cahaz4YS+eVb6wQLj8ib6nZkkS9P4=": {
            "valueMac": {
              "type": "Buffer",
              "data": "H1BSoTwN/4Ih9MOskJhXl6b25j4l/FI01whCjXkIRmA="
            }
          },
          "N4RDfxnwhd2UBrLqyD0Seg0aRrMPhkUNMclsd+W+Aqk=": {
            "valueMac": {
              "type": "Buffer",
              "data": "hxVfr87yL7Pt0jSVzk8MRMTtSTj1p7VerPWX8PD+20Y="
            }
          },
          "jlvEEKw3iS7aGBvPPTWuqRr6qlhC1PdychuXoNTWgAg=": {
            "valueMac": {
              "type": "Buffer",
              "data": "RfUa1YU95fOxvUoJjgVCswJOtuvXCRULqmcW+fRzv5I="
            }
          },
          "dJ8kHajQBpKimnyyKaPq4Rgkt9pUFSX1PuMkRpNnJDM=": {
            "valueMac": {
              "type": "Buffer",
              "data": "Dx+9UcZyhzWfrR2P/4WxC77Dr/1pWeucX6UG5eWIkik="
            }
          },
          "71Y0DibYVggWMazAs7FuVn3jJM0PEFVZZAtogaNT1PI=": {
            "valueMac": {
              "type": "Buffer",
              "data": "DUanvpqdMz3C3Kvr3x264WVvrEjVSB2KcmmziUzSMfc="
            }
          },
          "GhX7SjPqeIj8t9EUrW7lzawZAbVDC0hViyzmok1XPto=": {
            "valueMac": {
              "type": "Buffer",
              "data": "e0EDU/ygh0Y4N2ZLE70hMnn5qA11nmCWNP1B4lnXEBI="
            }
          },
          "FFOBW4u96FEDmOS6v5LjbjYgDopNUeeEx+b0gddx9No=": {
            "valueMac": {
              "type": "Buffer",
              "data": "hTHHOc6mtNYl+FzCRVQTpd2LETNRmi6822CNH6rpy68="
            }
          },
          "1DMvxHgn0NVwwtWUZVPYjA8MdC6FuukiQ4c7ACRLYEs=": {
            "valueMac": {
              "type": "Buffer",
              "data": "/aYYyL1OykMQHCY1jkadRkoOIoqcbMe8/wP+JizaUsY="
            }
          },
          "bD712bAouxOmo8/ESzDh1AhZtqGB51c/ESTOXAhRcXw=": {
            "valueMac": {
              "type": "Buffer",
              "data": "EK1Nn2QF1GKPCjQld11tsUv3wc+OMadN5qyaJXdBdVg="
            }
          },
          "dRyz6QHO2Jr0uXXCwPbHvzJVY2vdLYSBfGn5kMTM63Y=": {
            "valueMac": {
              "type": "Buffer",
              "data": "jlak0ylF28imu0fYyBH5Lljnfb/FJOhCLVMAxw8wVkg="
            }
          },
          "JgL59Q7Q/juDHU+/P48b3chO+YeT++f+XCpxRngeaWw=": {
            "valueMac": {
              "type": "Buffer",
              "data": "5ECTFm9Jh35o7/hias/NnoIcbg4rXRVli7FAF/agC60="
            }
          },
          "zsU2LM1Y/xz11duJR+DzGfT5z2fEFelCDa0Ohoxcpc4=": {
            "valueMac": {
              "type": "Buffer",
              "data": "jmU/8mpviG8a3JMPjh7b55C2Tfi0S9cx/VAF3Tvj7uk="
            }
          },
          "lDZ9nrNLExDyMGnF5XJdyk+KIXwI2kDgO303g41caHY=": {
            "valueMac": {
              "type": "Buffer",
              "data": "obIbaUUr+mifwWQ5NrtkyYJ9mAiYb+mXkVeaJ8Fa3n4="
            }
          },
          "xE6M2+nrIfwUIpAcM9q0dRoXtK2U6Of9EIEp9ThN8p8=": {
            "valueMac": {
              "type": "Buffer",
              "data": "J963uVsEz6mgn+3W3s0UoOJYsptwvFyOpGkuMIo+8wg="
            }
          },
          "+CfMZmlR+1eql31EN9H5RY52QKLQ4F0pAiTtNb5t5F8=": {
            "valueMac": {
              "type": "Buffer",
              "data": "bjmDSA5okQVTklnSEkophANsj/w7xe22iKQpIDJwCKo="
            }
          },
          "PUVebuxigBDxrFzZ7n3hQDEjwaipfC15YrdBM0FPeiY=": {
            "valueMac": {
              "type": "Buffer",
              "data": "PeZnm3mIFCr3n0BTXbdqB83baIh+hkZg8UYNUk0mGx0="
            }
          },
          "L7BQchM1FWx8XNeR6BY5PqWRlz5X/gdXnPn1JEkD6DA=": {
            "valueMac": {
              "type": "Buffer",
              "data": "XeBpxwzmuo3Jt2v6sO0BiKz3p0LfWLTYFE3SjyY9hS4="
            }
          },
          "DqQ3sNPVOfGA1yFLraA5raynrMpSPsUVawsJDuAtbMA=": {
            "valueMac": {
              "type": "Buffer",
              "data": "8hTCRSTwuAa49qr5BERFey+3tA8ETwFT2kIau+spNkU="
            }
          },
          "5CX+WD5xAHeITaxtjPlpAJen6hBeH1jnwJiUdiM8SLU=": {
            "valueMac": {
              "type": "Buffer",
              "data": "C2gOSPulMvFjnYSoEhZexWYBqhR4jTgl4MkIIbSKfzY="
            }
          },
          "Dg+g50Pu6ZsgvqVfCyDIlfP3hv0yAXoBwKwHU6wd+eM=": {
            "valueMac": {
              "type": "Buffer",
              "data": "xC56X1GljDsY27pCKJ3pKEiNVxN+TaDYTq2yDcZhnlc="
            }
          },
          "yz1AvcD8cxviEwsOwHE2bKOXI498eW1SyNScU2DdBl0=": {
            "valueMac": {
              "type": "Buffer",
              "data": "cUAA+Tr0RR3VEMa3mxea3j3s9pGo1JF1LRp9jrSjPKM="
            }
          },
          "gc21WjxhEMjkwsWQhW+kgIqPRKrN0lZeWhwQSVw/emI=": {
            "valueMac": {
              "type": "Buffer",
              "data": "zxGTIMC8YLzDLL1I29Mfy5KZIMosqXH7l0i3szLwKE0="
            }
          },
          "gXPyPP1bajgC+mSxScddNUW+F8cM8qbegwEnGk1Svrw=": {
            "valueMac": {
              "type": "Buffer",
              "data": "4/PMLWovhrR/CwK8IAOvGtibHY3lOGoQpaGbo4KrIUU="
            }
          },
          "kyZQkLli9v9SCCnO7hriC/BSrzPxk2AXlomv+P9QCuQ=": {
            "valueMac": {
              "type": "Buffer",
              "data": "BDnVFJyOBXvzsLr0ARY2EtWCMwR6xvf8Sg/tJpqQW5Y="
            }
          },
          "aBzzim2cYmW7mLznO6tJlTPHeNhu2IuuD0VyVT8s9wo=": {
            "valueMac": {
              "type": "Buffer",
              "data": "YVaxbUQiMuBieXgttCllOwlDK8vGYgeJB4AZri4WB/A="
            }
          },
          "SpwFgmQE5bL2wqQpPC074ZqkCd+VJY7+POwFeF4GEV0=": {
            "valueMac": {
              "type": "Buffer",
              "data": "RRbTSC7XmyAh3zM7FyhyZ5r6e2KEgMP+54v/4A+PGdY="
            }
          },
          "CdynRGG3YuiNVO4puBklI9Wa9yNkOyZBg+Q73aKDWX4=": {
            "valueMac": {
              "type": "Buffer",
              "data": "dQRHdZ7NqV6RyDdIqtJFMcAWgbvyOGiZaUFcM1wlsXs="
            }
          },
          "QqTVSQm5qX4Dqve7kISFwsKMdpgl32z4KM2ZHrQ9sSc=": {
            "valueMac": {
              "type": "Buffer",
              "data": "uNMXMny5B54ds7F1+mkc2SoIVcLn0KQ6q01Ogz0PdUM="
            }
          },
          "BMjjyscV8VXJnHO1vUhzD4HBCsrjY3H1vTVo/7VRYkk=": {
            "valueMac": {
              "type": "Buffer",
              "data": "PN76yEKRptjW4ZTVQZ0UAqh2KBsMwsPAcApuIShiPvE="
            }
          },
          "Geka6FEqRlrf4Uc6w0Hol8ynoWHqJy6MkPBK7Up4Fo8=": {
            "valueMac": {
              "type": "Buffer",
              "data": "l4j49vFEVzpFTzc5GE1im1g921iCcFenGBszkY2OUpc="
            }
          },
          "S70W88VMH/bwIe1igEIAcJmda3P1+cN2wzSLGkvdHAM=": {
            "valueMac": {
              "type": "Buffer",
              "data": "lA6A4fn3ZPny0Ek1ydsf6JMgHadIZ7/fTJrjGwfC5RI="
            }
          },
          "lMdJQqZM4vdOXFgyXxUhCDd/eYwCg4wpMkl6qhVlO1g=": {
            "valueMac": {
              "type": "Buffer",
              "data": "LNCypCn4F+IKqR8ofPgotR1U00LMkDjVrvVOwfQk9yg="
            }
          },
          "mDZSY8YLOvkv20RsoNRVeYYlmABsyFASwHvgUcp3joU=": {
            "valueMac": {
              "type": "Buffer",
              "data": "9PdhIwsJs/Bx0kCrqUo0LzBjCPjLL7sYx5kwETk07iA="
            }
          },
          "U6awi05sO552g7uZgy8R+t4Ykhw0CxQTNQHnfazV4B8=": {
            "valueMac": {
              "type": "Buffer",
              "data": "FKTw0RtmJGOcB8JeMabdOci4hfYsu3DiiBx2v+6braI="
            }
          },
          "j1GeAq3MMkBwYauQzJjI4dkxbsE/0ckP72Q1q0cnYrA=": {
            "valueMac": {
              "type": "Buffer",
              "data": "DWFPK1tDc0xR/AvBQ+OIOcw5SN/m6Xc1DKU6y9kYwFk="
            }
          },
          "NsdhMnyX3lNWTYhipSuObmwPY67ZzTOi91SbWQg9YLQ=": {
            "valueMac": {
              "type": "Buffer",
              "data": "ceIzNhGmTaIijCt8xXFrzT3dJAKXtR66RaeJrfkxog8="
            }
          },
          "ukQ3LVV1yfKzdD5dwQ46LzH9h29xdUGP9Z7IFEhB3UI=": {
            "valueMac": {
              "type": "Buffer",
              "data": "Unl4CjlwPTLi7mIofawJPoWxgSnJgWGT6YXxgMRnJVI="
            }
          },
          "LnTxsU6Eyappci4BvEzg/AWWkTFKjlRQ/BHCsPfj0OU=": {
            "valueMac": {
              "type": "Buffer",
              "data": "ctG+HbIgiDhYXDpgdcov+y14ieIvqfU571wDBJBKKSI="
            }
          },
          "B0UzPNAzzhk6qb7YY3ufNtBLDnLgo45QvSIORD9D4M4=": {
            "valueMac": {
              "type": "Buffer",
              "data": "V32MHkN2+Yp9yDGXQGCK3PDqc3FZDnObjdoNRWVE9xM="
            }
          },
          "WsNz3jJxhFxFOMgT/Bk8Oefv1H5m+1W2vDv9YayHBg0=": {
            "valueMac": {
              "type": "Buffer",
              "data": "mEdX3CKCyeplD3OkjkKvIO659XX8hjeyZsTuD1lXJ/I="
            }
          },
          "9AJLh0R33cRPXxLfUvuqJSLoGLRJuGNBFbp6KqWAPk8=": {
            "valueMac": {
              "type": "Buffer",
              "data": "dmwMUF7TsMdE0XpQFJ1KcBuq9oOlKYKMrqG7DPza420="
            }
          },
          "Hb1oDVolCSjbOnU5r1hqsNMNjiYoccbm407/4JWPOyI=": {
            "valueMac": {
              "type": "Buffer",
              "data": "OhiHN7kjPHsdhSXJ5x4EWPE6wYeSOuTOpV7LT+qcy84="
            }
          },
          "eG8I1qSBOyqgtvwjhPBhYF8ElYw2d5EHdKYpwR5pkM4=": {
            "valueMac": {
              "type": "Buffer",
              "data": "vLTJyCQIv1+MVv02MsMSB9ZYnSDnsvYkRHEVR4X301I="
            }
          },
          "KTmxQysTkzutOqSqxVxTLuH9IlFG4bd1K7CJJdyyqXs=": {
            "valueMac": {
              "type": "Buffer",
              "data": "VIRCvVlJAQIhG4rwdtPoyu4pBC68XFlwvVv7Ri3cmWM="
            }
          }
        }
      },
      "regular_low": {
        "version": 1,
        "hash": {
          "type": "Buffer",
          "data": "TeCKqQXiBJYB2SpR4b92ykB2jOX6Sxhg2X0j156AdcEcLTROAxoe2LYYum/4PHCXtM5JyxnElbSuphGCpsqbhaQ1Mqu2+fj3+sIUa6ma3/ZmNs60FgSu7+qXpPcKtbsqck1KWLLoxGOFM4/oYD/w/0pJ7Ah6A9SpnEwfOTy1i8w="
        },
        "indexValueMap": {
          "VaLTzU1Ie2VzNn64yMgGzWjc66MlCOS7DG89N3xQFPc=": {
            "valueMac": {
              "type": "Buffer",
              "data": "1SOzcmkgxUW7EabQkvQChnefGwgAxki00pYo2/9nz2A="
            }
          },
          "iwFkpt5dkqH7HZqloaHAYX4iRvl2SgWDU6ByoXEhXzg=": {
            "valueMac": {
              "type": "Buffer",
              "data": "t3v/H9pYE7ZB1cZ2oxr4E+BG4rccKUJw+Vd/jSBvNlM="
            }
          }
        }
      }
    },
    "senderKeys": {
      "120363031231603991@g.us::6283159644910::0": [
        {
          "senderKeyId": 1414850921,
          "senderChainKey": {
            "iteration": 2,
            "seed": "tdHcfUH59+0+psUhvzX+Mr2WpYJ+/erF0XoJliuJsBs="
          },
          "senderSigningKey": {
            "public": "BXfTuQQ15jL+pIRooDMaxarZ0lfHpkV7z/iRNGIFvaZI"
          }
        }
      ],
      "status@broadcast::62895329406541::0": [
        {
          "senderKeyId": 1482034781,
          "senderChainKey": {
            "iteration": 6,
            "seed": "cThStKMvK4e/fk+CbnQ9Brg+1fvWtxxWa9P1LAvWgIQ="
          },
          "senderSigningKey": {
            "public": "BUKoq1iba0O/vkovBMCUbBmBccaWzP1wWPQBgzlav9U8"
          }
        }
      ],
      "120363044249487754@g.us::6281998199848::0": [
        {
          "senderKeyId": 876307888,
          "senderChainKey": {
            "iteration": 1,
            "seed": "eo+2tC8BUfSBMmjNpI3tTjO6SK4ZUttatQ/r4q3fYhU="
          },
          "senderSigningKey": {
            "public": "BTRtBDlMU+XA3cfWIkR2PCR0tq5VtpL8umajYGbSN24C"
          }
        }
      ]
    }
  }
}